addition_lpkapil/__init__.py
addition_lpkapil/addition.py
addition_lpkapil-0.0.2.dist-info/METADATA
addition_lpkapil-0.0.2.dist-info/WHEEL
addition_lpkapil-0.0.2.dist-info/licenses/LICENSE
addition_lpkapil-0.0.2.dist-info/RECORD
