Metadata-Version: 2.1
Name: addition_lpkapil
Version: 0.0.2
Summary: A small two numbers addition package
Project-URL: Homepage, https://github.com/lpkapil/addition_lpkapil
Project-URL: Issues, https://github.com/lpkapil/addition_lpkapil/issues
Author-email: Kapil Yadav <lpkapil@gmail.com>
License-File: LICENSE
Classifier: License :: OSI Approved :: MIT License
Classifier: Operating System :: OS Independent
Classifier: Programming Language :: Python :: 3
Requires-Python: >=3.8
